fosslight_source/__init__.py
fosslight_source/_help.py
fosslight_source/_license_matched.py
fosslight_source/_parsing_scancode_file_item.py
fosslight_source/_parsing_scanoss_file.py
fosslight_source/_scan_item.py
fosslight_source/cli.py
fosslight_source/run_scancode.py
fosslight_source/run_scanoss.py
fosslight_source/run_spdx_extractor.py
fosslight_source-2.2.1.dist-info/licenses/LICENSE
fosslight_source-2.2.1.dist-info/METADATA
fosslight_source-2.2.1.dist-info/WHEEL
fosslight_source-2.2.1.dist-info/entry_points.txt
fosslight_source-2.2.1.dist-info/top_level.txt
fosslight_source-2.2.1.dist-info/RECORD
