Metadata-Version: 2.4
Name: fosslight_source
Version: 2.2.1
Summary: FOSSLight Source Scanner
Home-page: https://github.com/fosslight/fosslight_source_scanner
Download-URL: https://github.com/fosslight/fosslight_source_scanner
Author: LG Electronics
License: Apache-2.0
Classifier: License :: OSI Approved :: Apache Software License
Classifier: Programming Language :: Python :: 3
Classifier: Programming Language :: Python :: 3.10
Classifier: Programming Language :: Python :: 3.11
Classifier: Programming Language :: Python :: 3.12
Requires-Python: >=3.10, <3.13
License-File: LICENSE
Requires-Dist: pyparsing
Requires-Dist: scanoss>=1.18.0
Requires-Dist: XlsxWriter
Requires-Dist: fosslight_util>=2.1.34
Requires-Dist: PyYAML
Requires-Dist: wheel>=0.38.1
Requires-Dist: intbitset
Requires-Dist: fosslight_binary>=5.0.0
Requires-Dist: scancode-toolkit>=32.0.2
Requires-Dist: fingerprints==1.2.3
Requires-Dist: normality==2.6.1
Requires-Dist: click==8.2.1
Dynamic: author
Dynamic: classifier
Dynamic: description
Dynamic: description-content-type
Dynamic: download-url
Dynamic: home-page
Dynamic: license
Dynamic: license-file
Dynamic: requires-dist
Dynamic: requires-python
Dynamic: summary
